EverythingLib/__init__.py
EverythingLib/main.py
everythinglib-0.0.1.dist-info/METADATA
everythinglib-0.0.1.dist-info/WHEEL
everythinglib-0.0.1.dist-info/licenses/LICENSE
everythinglib-0.0.1.dist-info/RECORD
