Metadata-Version: 2.3
Name: EverythingLib
Version: 0.0.1
Summary: This library is created to simplify some python things
Author-email: Kirilchuk Mikhail <kirilchukmikhail11@yandex.ru>
License-File: LICENSE
Classifier: License :: OSI Approved :: MIT License
Classifier: Operating System :: OS Independent
Classifier: Programming Language :: Python :: 3
Requires-Python: >=3.10.0
